README.rst
setup.py
django_nodetree.egg-info/PKG-INFO
django_nodetree.egg-info/SOURCES.txt
django_nodetree.egg-info/dependency_links.txt
django_nodetree.egg-info/top_level.txt
nodetree/__init__.py
nodetree/apps.py
nodetree/exceptions.py
nodetree/fields.py
nodetree/filters.py
nodetree/maps.py
nodetree/models.py
nodetree/nodetypes.py
nodetree/permissions.py
nodetree/serializers.py
nodetree/settings.py
nodetree/viewsets.py
nodetree/migrations/0001_initial.py
nodetree/migrations/__init__.py
nodetree/runtests/__init__.py
nodetree/runtests/runtests.py
nodetree/runtests/settings.py
nodetree/runtests/urls.py
nodetree/tests/__init__.py
nodetree/tests/apps.py
nodetree/tests/filters.py
nodetree/tests/maps.py
nodetree/tests/models.py
nodetree/tests/modeltests.py
nodetree/tests/nodetypes.py
nodetree/tests/nodetypetests.py
nodetree/tests/permissions.py
nodetree/tests/relations_generic.py
nodetree/tests/relations_recursive.py
nodetree/tests/serializers.py
nodetree/tests/settings.py
nodetree/tests/tests.py
nodetree/tests/viewsets.py