Metadata-Version: 1.0
Name: django-nodetree
Version: 0.1.1
Summary: Library to help creating API's that handle contents in a ordered tree data structure with Django.
Home-page: https://github.com/lukasbuenger/nodetree
Author: Lukas Buenger
Author-email: lukasbuenger@gmail.com
License: BSD
Download-URL: http://pypi.python.org/pypi/nodetree/
Platform: UNKNOWN
Classifier: Development Status :: 5 - Production/Stable
Classifier: Environment :: Web Environment
Classifier: Intended Audience :: Developers
Classifier: License :: OSI Approved :: BSD License
Classifier: Operating System :: OS Independent
Classifier: Programming Language :: Python
Classifier: Programming Language :: Python :: 3
Classifier: Topic :: Internet :: WWW/HTTP
